{"id":"aplicaci-n-cad---funcionalidades-principales;seleccionar-herramienta-de-c-rculo;firefox-149-0-2;mac","name":"Seleccionar herramienta de círculo","title":"Seleccionar herramienta de círculo","manual":false,"testSteps":[{"number":1,"description":"Before","startTime":"2026-04-22T19:22:32.826Z","children":[],"reportData":[],"screenshots":[],"duration":0,"result":"SUCCESS"},{"number":2,"description":"Dado que el usuario abre la aplicación CAD","startTime":"2026-04-22T19:22:32.826Z","children":[{"number":3,"description":"Diseñador abre la aplicación CAD en http://localhost:5173","startTime":"2026-04-22T19:22:32.836Z","children":[{"number":4,"description":"Diseñador navigates to &quot;http://localhost:5173&quot;","startTime":"2026-04-22T19:22:32.836Z","children":[],"reportData":[],"screenshots":[],"duration":2452,"result":"SUCCESS"}],"reportData":[],"screenshots":[],"duration":2465,"result":"SUCCESS"},{"number":5,"description":"Diseñador waits until que el overlay de inicialización no bloquea la UI does equal true","startTime":"2026-04-22T19:22:35.313Z","children":[],"reportData":[],"screenshots":[],"duration":20166,"result":"SUCCESS"}],"reportData":[],"screenshots":[],"duration":22672,"result":"SUCCESS"},{"number":6,"description":"Cuando el usuario selecciona la herramienta &quot;Círculo (C)&quot;","startTime":"2026-04-22T19:22:55.499Z","children":[{"number":7,"description":"Diseñador hace click en la herramienta Círculo (C)","startTime":"2026-04-22T19:22:55.516Z","children":[{"number":8,"description":"Diseñador waits until que el overlay de inicialización no bloquea la UI does equal true","startTime":"2026-04-22T19:22:55.518Z","children":[],"reportData":[],"screenshots":[],"duration":59,"result":"SUCCESS"},{"number":9,"description":"Diseñador waits for 500ms","startTime":"2026-04-22T19:22:55.588Z","children":[],"reportData":[],"screenshots":[],"duration":506,"result":"SUCCESS"},{"number":10,"description":"Diseñador clicks on page element located by css (&apos;[title=&quot;Círculo (C)&quot;]&apos;)","startTime":"2026-04-22T19:22:56.106Z","children":[],"reportData":[],"screenshots":[],"duration":586,"result":"SUCCESS"}],"reportData":[],"screenshots":[],"duration":1189,"result":"SUCCESS"}],"reportData":[],"screenshots":[],"duration":1221,"result":"SUCCESS"},{"number":11,"description":"Entonces la herramienta &quot;Círculo (C)&quot; debería estar activa","startTime":"2026-04-22T19:22:56.721Z","children":[{"number":12,"description":"Diseñador ensures that que la herramienta &quot;Círculo (C)&quot; está activa does equal true","startTime":"2026-04-22T19:22:56.735Z","children":[],"reportData":[],"screenshots":[],"duration":54,"result":"SUCCESS"}],"reportData":[],"screenshots":[],"duration":80,"result":"SUCCESS"},{"number":13,"description":"After","startTime":"2026-04-22T19:22:56.802Z","children":[],"reportData":[],"screenshots":[],"duration":3,"result":"SUCCESS"}],"userStory":{"id":"aplicaci-n-cad---funcionalidades-principales","storyName":"Aplicación CAD — Funcionalidades principales","displayName":"Aplicación CAD — Funcionalidades principales","path":"cad-app","type":"feature","narrative":"Como diseñador que trabaja con modelos 3D\nQuiero usar la aplicación CAD en el navegador\nPara crear y editar bocetos y modelos tridimensionales","pathElements":[{"name":"cad-app","description":"Cad-app"}]},"startTime":"2026-04-22T19:22:32.825Z","context":"firefox,mac","driver":"firefox","tags":[{"name":"firefox 149.0.2","type":"browser","browserName":"firefox","browserVersion":"149.0.2","displayName":"firefox 149.0.2"},{"name":"mac","type":"platform","platformName":"mac","platformVersion":"","displayName":"mac"},{"name":"Aplicación CAD — Funcionalidades principales","type":"feature","displayName":"Aplicación CAD — Funcionalidades principales"}],"testSource":"JS","featureTag":{"name":"Aplicación CAD — Funcionalidades principales","type":"feature","displayName":"Aplicación CAD — Funcionalidades principales"},"actors":[{"name":"Diseñador","can":["PerformActivities","AnswerQuestions","RaiseErrors","ScheduleWork { scheduler: { clock: { timeAdjustment: { milliseconds: 0 } }, interactionTimeout: { milliseconds: 5000 } } }","BrowseTheWeb (BrowseTheWebWithWebdriverIO)"]}],"result":"SUCCESS","duration":24008}